biz_agent_hub/__init__.py
biz_agent_hub/analytics_agent.py
biz_agent_hub/biz_agent_hub.py
biz_agent_hub/scrap_agent.py
biz_agent_hub/support_agent.py
biz_agent_hub/ui_testing_agent.py
biz_agent_hub-0.0.4.dist-info/METADATA
biz_agent_hub-0.0.4.dist-info/WHEEL
biz_agent_hub-0.0.4.dist-info/top_level.txt
biz_agent_hub-0.0.4.dist-info/RECORD
