Metadata-Version: 2.4
Name: biz_agent_hub
Version: 0.0.4
Summary: Biz Agent Hub Python SDK
Author-email: Mustafa Abusharkh <mabusharkh@bizagenthub.ai>
Classifier: Programming Language :: Python :: 3
Classifier: License :: OSI Approved :: MIT License
Classifier: Operating System :: OS Independent
Requires-Python: >=3.9
Requires-Dist: requests>=2.0.0
